.editorconfig
.gitignore
LICENSE
README.md
setup.py
tox.ini
girder_monkeybrains/__init__.py
girder_monkeybrains.egg-info/PKG-INFO
girder_monkeybrains.egg-info/SOURCES.txt
girder_monkeybrains.egg-info/dependency_links.txt
girder_monkeybrains.egg-info/entry_points.txt
girder_monkeybrains.egg-info/requires.txt
girder_monkeybrains.egg-info/top_level.txt
girder_monkeybrains/web_client/CollectionView.js
girder_monkeybrains/web_client/EditCollectionWidget.js
girder_monkeybrains/web_client/longitude-d3.js
girder_monkeybrains/web_client/main.js
girder_monkeybrains/web_client/package.json
girder_monkeybrains/web_client/stylesheets/collectionInfopage.styl
girder_monkeybrains/web_client/stylesheets/longitude.styl
girder_monkeybrains/web_client/templates/collectionInfopage.pug
girder_monkeybrains/web_client/templates/editCollectionInfopage.pug
girder_monkeybrains/web_client/views/InfoPageWidget.js
utils/create_tree_from_metadata.py
utils/metadata.json
utils/set_metadata.py
utils/set_single_subj_metadata.py