Metadata-Version: 2.1
Name: girder-monkeybrains
Version: 1.0.3
Summary: Displays monkey neurodevelopmental data.
Home-page: https://github.com/girder/monkeybrains
Maintainer: Kitware, Inc.
Maintainer-email: kitware@kitware.com
License: UNKNOWN
Platform: UNKNOWN
